simpleschema/__init__.py
simpleschema/__version__.py
simpleschema/exceptions.py
simpleschema/helper_classes.py
simpleschema/matchers.py
simpleschema/validate.py
simpleschema-0.9.0.dist-info/LICENSE
simpleschema-0.9.0.dist-info/METADATA
simpleschema-0.9.0.dist-info/WHEEL
simpleschema-0.9.0.dist-info/top_level.txt
simpleschema-0.9.0.dist-info/RECORD
