Metadata-Version: 2.1
Name: simpleschema
Version: 0.9.0
Summary: A minimal schema validator
Home-page: https://github.com/Lrizika/simpleschema
Author: Lrizika
Author-email: lrizika.simpleschema@lrizika.com
License: MIT
Requires-Python: >=3.8.0
License-File: LICENSE
